solace_semp_action/__init__.py
solace_semp_action/api_client.py
solace_semp_action/configuration.py
solace_semp_action/rest.py
solace_semp_action/api/__init__.py
solace_semp_action/api/about_api.py
solace_semp_action/api/all_api.py
solace_semp_action/api/authentication_oauth_provider_api.py
solace_semp_action/api/bridge_api.py
solace_semp_action/api/cert_authority_api.py
solace_semp_action/api/client_api.py
solace_semp_action/api/client_cert_authority_api.py
solace_semp_action/api/distributed_cache_api.py
solace_semp_action/api/mqtt_session_api.py
solace_semp_action/api/msg_vpn_api.py
solace_semp_action/api/queue_api.py
solace_semp_action/api/replay_log_api.py
solace_semp_action/api/rest_delivery_point_api.py
solace_semp_action/api/topic_endpoint_api.py
solace_semp_action/api/transaction_api.py
solace_semp_action/models/__init__.py
solace_semp_action/models/about.py
solace_semp_action/models/about_api.py
solace_semp_action/models/about_api_links.py
solace_semp_action/models/about_api_response.py
solace_semp_action/models/about_links.py
solace_semp_action/models/about_response.py
solace_semp_action/models/about_user.py
solace_semp_action/models/about_user_links.py
solace_semp_action/models/about_user_msg_vpn.py
solace_semp_action/models/about_user_msg_vpn_links.py
solace_semp_action/models/about_user_msg_vpn_response.py
solace_semp_action/models/about_user_msg_vpns_response.py
solace_semp_action/models/about_user_response.py
solace_semp_action/models/broker.py
solace_semp_action/models/broker_links.py
solace_semp_action/models/broker_response.py
solace_semp_action/models/cert_authorities_response.py
solace_semp_action/models/cert_authority.py
solace_semp_action/models/cert_authority_links.py
solace_semp_action/models/cert_authority_refresh_crl.py
solace_semp_action/models/cert_authority_response.py
solace_semp_action/models/client_cert_authorities_response.py
solace_semp_action/models/client_cert_authority.py
solace_semp_action/models/client_cert_authority_links.py
solace_semp_action-9.8.0.12.dist-info/METADATA
solace_semp_action-9.8.0.12.dist-info/WHEEL
solace_semp_action-9.8.0.12.dist-info/top_level.txt
solace_semp_action-9.8.0.12.dist-info/RECORD
